bitcoinrpcasync/__init__.py
bitcoinrpcasync/authproxy.py
python_bitcoinrpc_async-1.0.0.dist-info/LICENSE
python_bitcoinrpc_async-1.0.0.dist-info/METADATA
python_bitcoinrpc_async-1.0.0.dist-info/WHEEL
python_bitcoinrpc_async-1.0.0.dist-info/top_level.txt
python_bitcoinrpc_async-1.0.0.dist-info/RECORD
