Metadata-Version: 2.1
Name: python-bitcoinrpc-async
Version: 1.0.0
Summary: Enhanced version of python-jsonrpc for use with Bitcoin, for async use.
Home-page: https://github.com/reuben-s/python-bitcoinrpc-async
Author: Reuben S
Maintainer: Reuben S
License: 
Project-URL: Homepage, https://github.com/reuben-s/python-bitcoinrpc-async
Keywords: bitcoin,async,bitcoincore
Classifier: License :: OSI Approved :: GNU Library or Lesser General Public License (LGPL)
Classifier: Programming Language :: Python
Classifier: Programming Language :: Python :: 3
Requires-Python: >=3.9
License-File: LICENSE
Requires-Dist: aiohttp
